{
	"schemaVersion": 1,
	"id": "blight",
	"version": "${version}",
	"name": "Tutorial Mod",
	"description": "This is a Tutorial Mod made by Kaupenjoe :)",
	"authors": [
		"Kaupenjoe!"
	],
	"contact": {
		"homepage": "https://fabricmc.net/",
		"sources": "https://github.com/FabricMC/fabric-example-mod"
	},
	"license": "MIT",
	"icon": "assets/blight/icon.png",
	"environment": "*",
	"entrypoints": {
		"main": [
			"net.statdefender.blight.Blight"
		],
		"client": [
			"net.statdefender.blight.BlightClient"
		],
		"fabric-datagen": [
			"net.statdefender.blight.BlightDataGenerator"
		]
	},
	"mixins": [
		"blight.mixins.json"
	],
	"depends": {
		"fabricloader": ">=0.14.21",
		"minecraft": "~1.20.1",
		"java": ">=17",
		"fabric-api": "*"
	},
	"suggests": {
		"another-mod": "*"
	}
}